pygame_gameover/__init__.py
pygame_gameover/gameover.py
pygame_gameover-0.0.4.dist-info/LICENSE.TXT
pygame_gameover-0.0.4.dist-info/METADATA
pygame_gameover-0.0.4.dist-info/WHEEL
pygame_gameover-0.0.4.dist-info/top_level.txt
pygame_gameover-0.0.4.dist-info/RECORD
