Metadata-Version: 2.1
Name: pygame-gameover
Version: 0.0.4
Summary: It game gameover module
Home-page: https://github.com/kurban-hussain-786/MY-CODE
Author: kurban hussain
Author-email: kurbanhussain086@gmail.com
License: MIT
Keywords: gameover in pygame,pygame gameover,gameover,over game,game over,pygame_gameover,gameover_pygame,pygame game,pygame,pygame GAMEOVER
Classifier: License :: OSI Approved :: MIT License
Classifier: Programming Language :: Python :: 3.6
Classifier: Programming Language :: Python :: 3.7
Classifier: Programming Language :: Python :: 3.8
License-File: LICENSE.TXT
